numpoly/__init__.py
numpoly/align.py
numpoly/baseclass.py
numpoly/dispatch.py
numpoly/option.py
numpoly/sympy_.py
numpoly/array_function/__init__.py
numpoly/array_function/absolute.py
numpoly/array_function/add.py
numpoly/array_function/all.py
numpoly/array_function/allclose.py
numpoly/array_function/amax.py
numpoly/array_function/amin.py
numpoly/array_function/any.py
numpoly/array_function/apply_along_axis.py
numpoly/array_function/apply_over_axes.py
numpoly/array_function/argmax.py
numpoly/array_function/argmin.py
numpoly/array_function/around.py
numpoly/array_function/array_repr.py
numpoly/array_function/array_split.py
numpoly/array_function/array_str.py
numpoly/array_function/atleast_1d.py
numpoly/array_function/atleast_2d.py
numpoly/array_function/atleast_3d.py
numpoly/array_function/broadcast_arrays.py
numpoly/array_function/ceil.py
numpoly/array_function/choose.py
numpoly/array_function/common_type.py
numpoly/array_function/concatenate.py
numpoly/array_function/copyto.py
numpoly/array_function/count_nonzero.py
numpoly/array_function/cumsum.py
numpoly/array_function/det.py
numpoly/array_function/diag.py
numpoly/array_function/diagonal.py
numpoly/array_function/diff.py
numpoly/array_function/divmod.py
numpoly/array_function/dsplit.py
numpoly/array_function/dstack.py
numpoly/array_function/ediff1d.py
numpoly/array_function/equal.py
numpoly/array_function/expand_dims.py
numpoly/array_function/floor.py
numpoly/array_function/floor_divide.py
numpoly/array_function/full.py
numpoly/array_function/full_like.py
numpoly/array_function/greater.py
numpoly/array_function/greater_equal.py
numpoly/array_function/hsplit.py
numpoly/array_function/hstack.py
numpoly/array_function/inner.py
numpoly/array_function/isclose.py
numpoly/array_function/isfinite.py
numpoly/array_function/less.py
numpoly/array_function/less_equal.py
numpoly/array_function/load.py
numpoly/array_function/loadtxt.py
numpoly/array_function/logical_and.py
numpoly/array_function/logical_or.py
numpoly-1.2.14.dist-info/LICENSE
numpoly-1.2.14.dist-info/METADATA
numpoly-1.2.14.dist-info/WHEEL
numpoly-1.2.14.dist-info/top_level.txt
numpoly-1.2.14.dist-info/RECORD
