Metadata-Version: 2.1
Name: numpoly
Version: 1.2.14
Summary: Polynomials as a numpy datatype
License: BSD-2-Clause
Classifier: Development Status :: 5 - Production/Stable
Classifier: Intended Audience :: Science/Research
Classifier: Topic :: Scientific/Engineering :: Mathematics
Classifier: License :: OSI Approved :: BSD License
Classifier: Natural Language :: English
Requires-Python: >=3.7
License-File: LICENSE
Requires-Dist: numpy>=1.20
Requires-Dist: setuptools>=40.9.0
Requires-Dist: importlib-metadata
Provides-Extra: dev
Requires-Dist: black==23.3.0; extra == "dev"
Requires-Dist: pylint==2.15.5; extra == "dev"
Requires-Dist: pydocstyle==3.0.0; extra == "dev"
Requires-Dist: pydata_sphinx_theme==0.15.2; extra == "dev"
Requires-Dist: sympy; extra == "dev"
Requires-Dist: pytest; extra == "dev"
Requires-Dist: pytest-cov; extra == "dev"
Requires-Dist: codecov; extra == "dev"
Requires-Dist: coverage>=5.0; extra == "dev"
Requires-Dist: Sphinx; extra == "dev"
Requires-Dist: sphinx_automodapi; extra == "dev"
